torreq/__init__.py
torreq/onion_requests.py
torreq-1.0.dist-info/METADATA
torreq-1.0.dist-info/WHEEL
torreq-1.0.dist-info/top_level.txt
torreq-1.0.dist-info/RECORD
